{
  "annotations": {"list": []},
  "editable": true,
  "fiscalYearStartMonth": 0,
  "graphTooltip": 0,
  "links": [],
  "panels": [
    {"datasource": {"type": "prometheus", "uid": "prometheus"}, "fieldConfig": {"defaults": {"thresholds": {"mode": "absolute", "steps": [{"color": "red", "value": null}, {"color": "green", "value": 4}]}, "unit": "none"}, "overrides": []}, "gridPos": {"h": 5, "w": 6, "x": 0, "y": 0}, "id": 1, "options": {"colorMode": "background", "graphMode": "none", "reduceOptions": {"calcs": ["lastNotNull"], "fields": "", "values": false}, "textMode": "auto"}, "targets": [{"expr": "sum(up{namespace=\"flux-system\",service=~\".*metrics\"})", "refId": "A"}], "title": "Flux Targets Up", "type": "stat"},
    {"datasource": {"type": "prometheus", "uid": "prometheus"}, "fieldConfig": {"defaults": {"unit": "none"}, "overrides": []}, "gridPos": {"h": 5, "w": 6, "x": 6, "y": 0}, "id": 2, "options": {"colorMode": "background", "graphMode": "none", "reduceOptions": {"calcs": ["lastNotNull"], "fields": "", "values": false}, "textMode": "auto"}, "targets": [{"expr": "sum(rate(controller_runtime_reconcile_errors_total{namespace=\"flux-system\"}[5m]))", "refId": "A"}], "title": "Reconcile Errors / sec", "type": "stat"},
    {"datasource": {"type": "prometheus", "uid": "prometheus"}, "fieldConfig": {"defaults": {"unit": "none"}, "overrides": []}, "gridPos": {"h": 8, "w": 12, "x": 0, "y": 5}, "id": 3, "targets": [{"expr": "sum by (service) (up{namespace=\"flux-system\",service=~\".*metrics\"})", "legendFormat": "{{service}}", "refId": "A"}], "title": "Flux Controller Availability", "type": "timeseries"},
    {"datasource": {"type": "prometheus", "uid": "prometheus"}, "fieldConfig": {"defaults": {"unit": "s"}, "overrides": []}, "gridPos": {"h": 8, "w": 12, "x": 12, "y": 5}, "id": 4, "targets": [{"expr": "histogram_quantile(0.95, sum by (le, controller) (rate(controller_runtime_reconcile_time_seconds_bucket{namespace=\"flux-system\"}[5m])))", "legendFormat": "{{controller}}", "refId": "A"}], "title": "Flux Reconcile P95", "type": "timeseries"},
    {"datasource": {"type": "prometheus", "uid": "prometheus"}, "fieldConfig": {"defaults": {"unit": "none"}, "overrides": []}, "gridPos": {"h": 8, "w": 12, "x": 0, "y": 13}, "id": 5, "targets": [{"expr": "sum by (kind, name) (gotk_reconcile_condition{namespace=\"flux-system\",type=\"Ready\",status=\"true\"})", "legendFormat": "{{kind}}/{{name}}", "refId": "A"}], "title": "Flux Ready Conditions", "type": "timeseries"},
    {"datasource": {"type": "prometheus", "uid": "prometheus"}, "fieldConfig": {"defaults": {"unit": "none"}, "overrides": []}, "gridPos": {"h": 8, "w": 12, "x": 12, "y": 13}, "id": 6, "targets": [{"expr": "sum by (controller) (workqueue_depth{namespace=\"flux-system\"})", "legendFormat": "{{controller}}", "refId": "A"}], "title": "Flux Workqueue Depth", "type": "timeseries"}
  ],
  "refresh": "30s",
  "schemaVersion": 39,
  "style": "dark",
  "tags": ["prometheus", "flux"],
  "templating": {"list": []},
  "time": {"from": "now-6h", "to": "now"},
  "timezone": "browser",
  "title": "Prometheus - Flux Health",
  "uid": "prom-flux-health",
  "version": 1
}
